{
  "purva clermont": "Purva Clermont",
  "chembur, mumbai": "Chembur, Mumbai",
  "purva silversands": "Purva Silversands",
  "pune": "Pune",
  "2 bhk": "2 BHK",
  "purva aspire": "Purva Aspire",
  "bavdhan": "Bavdhan",
  "purva zenium": "Purva Zenium",
  "international airport road": "International Airport Road",
  "3 bhk": "3 BHK",
  "purva blubelle": "Purva Blubelle",
  "rajajinagar": "Rajajinagar",
  "purva emerald bay": "Purva Emerald Bay",
  "mundhwa, pune": "Mundhwa, Pune",
  "south": "South",
  "east": "East",
  "north": "North",
  "west": "West"
}